mailpytm/__init__.py
mailpytm/exceptions.py
mailpytm/mailpytm.py
mailpytm-1.1.0.dist-info/licenses/LICENSE
mailpytm-1.1.0.dist-info/METADATA
mailpytm-1.1.0.dist-info/WHEEL
mailpytm-1.1.0.dist-info/top_level.txt
mailpytm-1.1.0.dist-info/RECORD
