Metadata-Version: 2.4
Name: mailpytm
Version: 1.1.0
Summary: Python wrapper for mail.tm disposable email service
Home-page: https://github.com/cvcvka5/mailpytm
Author: Ulus Vatansever
Author-email: ulusvatansever@gmail.com
License: MIT
Project-URL: Homepage, https://github.com/cvcvka5/mailpytm
Project-URL: License, https://github.com/cvcvka5/mailpytm/blob/master/LICENSE
Requires-Python: >=3.7
License-File: LICENSE
Dynamic: author
Dynamic: author-email
Dynamic: home-page
Dynamic: license-file
Dynamic: requires-python
